{"mapwidth":3500,"mapheight":2735,"categories":[{"id":"34","title":"Atractivos tur\u00edsticos","color":"#bb0000","show":"true"},{"id":"32","title":"Emplazamientos arqueol\u00f3gicos","color":"#bb0000","show":"true"}],"levels":[{"id":"map-4","name":"yucatan","title":"Mapa de Yucat\u00e1n","map":"http:\/\/localhost\/interactive-map\/www\/wp-content\/uploads\/yucatan-big-but-low-es2-3500x2735.jpg","minimap":"http:\/\/localhost\/interactive-map\/www\/wp-content\/uploads\/yucatan-big-but-low-es2-150x150.jpg","locations":[{"id":150,"title":"Isla Mujeres","about":"","description":"A 30 minutos de Canc\u00fan","iink":null,"category":34,"thumbnail":"http:\/\/localhost\/interactive-map\/www\/wp-content\/uploads\/isla-mujeres-mapa-150x150.jpg","x":0.8,"y":0.19,"link":"http:\/\/localhost\/interactive-map\/www\/mapa\/isla-mujeres\/","zoom":"2"},{"id":109,"title":"Chich\u00e9n-Itza","about":"7a maravilla del mundo","description":"Descripci\u00f3n de una l\u00ednea","iink":null,"category":32,"thumbnail":"http:\/\/localhost\/interactive-map\/www\/wp-content\/uploads\/icon-chichen.png","x":0.47,"y":0.28,"link":"http:\/\/localhost\/interactive-map\/www\/mapa\/mapa-chichen-itza\/","zoom":"2"},{"id":130,"title":"Uxmal","about":"","description":"Ciudad maya en la jungla","iink":null,"category":32,"thumbnail":null,"x":0.4,"y":0.25,"link":"javascript:   abreLocationCard('\r\no->post_name')","zoom":"2"},{"id":92,"title":"Tul\u00fam","about":"","description":"test","iink":null,"category":34,"thumbnail":null,"x":0.5,"y":0.5,"link":"javascript:   abreLocationCard('\r\no->post_name')","zoom":"2"}]},{"id":"map-17","name":"mapa-chichen-itza","title":"Mapa de Chich\u00e9n Itz\u00e1","map":"http:\/\/localhost\/interactive-map\/www\/wp-content\/uploads\/mapa-chichen-70ppi1.jpg","minimap":"http:\/\/localhost\/interactive-map\/www\/wp-content\/uploads\/mapa-chichen-70ppi1-150x150.jpg","locations":[{"id":20,"title":"Pir\u00e1mide de Kukulk\u00e1n","about":"","description":"En el centro del complejo","iink":null,"category":null,"thumbnail":"http:\/\/localhost\/interactive-map\/www\/wp-content\/uploads\/icon-chichen.png","x":0.36,"y":0.45,"link":false,"zoom":"2"}]},{"id":"map-147","name":"isla-mujeres","title":"Isla Mujeres Mapa","map":"http:\/\/localhost\/interactive-map\/www\/wp-content\/uploads\/isla-mujeres-mapa-3500x862.jpg","minimap":"http:\/\/localhost\/interactive-map\/www\/wp-content\/uploads\/isla-mujeres-mapa-150x150.jpg","locations":[{"id":153,"title":"Templo Maya","about":"","description":"Templo maya en la punta sur","iink":null,"category":null,"thumbnail":"http:\/\/localhost\/interactive-map\/www\/wp-content\/uploads\/icon-chichen.png","x":0.97,"y":0.65,"link":false,"zoom":"2"}]}]}